vault12factor/__init__.py
vault12factor/apps.py
12factor_vault-0.1.23.dist-info/LICENSE
12factor_vault-0.1.23.dist-info/METADATA
12factor_vault-0.1.23.dist-info/WHEEL
12factor_vault-0.1.23.dist-info/top_level.txt
12factor_vault-0.1.23.dist-info/RECORD
