Metadata-Version: 2.1
Name: 12factor-vault
Version: 0.1.23
Summary: Helper classes to integrate Django and other projects with Vault
Home-page: https://github.com/jdelic/12factor-vault/
Author: Jonas Maurus (@jdelic)
Author-email: jonas-12factor-vault@gopythongo.com
Maintainer: GoPythonGo.com
Maintainer-email: info@gopythongo.com
License: UNKNOWN
Platform: UNKNOWN
Classifier: Development Status :: 4 - Beta
Classifier: Intended Audience :: Developers
Classifier: Intended Audience :: System Administrators
Classifier: Programming Language :: Python :: 3 :: Only
Classifier: License :: OSI Approved :: BSD License
Classifier: Operating System :: POSIX
License-File: LICENSE
Requires-Dist: hvac (>=0.3.0)
Requires-Dist: django-dbconn-retry (>=0.1.5)
